ndstextgen/__init__.py
ndstextgen/__main__.py
ndstextgen/cli.py
ndstextgen-1.5.0.dist-info/LICENSE
ndstextgen-1.5.0.dist-info/METADATA
ndstextgen-1.5.0.dist-info/WHEEL
ndstextgen-1.5.0.dist-info/entry_points.txt
ndstextgen-1.5.0.dist-info/top_level.txt
ndstextgen-1.5.0.dist-info/RECORD
