Metadata-Version: 2.1
Name: ndstextgen
Version: 1.5.0
Summary: Command line tool to render text from NDS .NFTR fonts.
Home-page: https://github.com/Illidanz/ndstextgen
Author: Illidan
License: UNKNOWN
Platform: UNKNOWN
Classifier: Programming Language :: Python :: 3
Classifier: License :: OSI Approved :: MIT License
Classifier: Operating System :: OS Independent
Requires-Python: >=3.7
Requires-Dist: hacktools (>=0.11)
